sqlshell/__init__.py
sqlshell/__main__.py
sqlshell/ai_autocomplete.py
sqlshell/ai_settings_dialog.py
sqlshell/christmas_theme.py
sqlshell/context_suggester.py
sqlshell/create_test_data.py
sqlshell/docs_panel.py
sqlshell/duckdb_docs_lookup.py
sqlshell/editor.py
sqlshell/editor_integration.py
sqlshell/execution_handler.py
sqlshell/menus.py
sqlshell/notification_manager.py
sqlshell/project_manager.py
sqlshell/query_tab.py
sqlshell/space_invaders.py
sqlshell/splash_screen.py
sqlshell/sqlshell_demo.png
sqlshell/styles.py
sqlshell/suggester_integration.py
sqlshell/syntax_highlighter.py
sqlshell/table_list.py
sqlshell/widgets.py
sqlshell/data/create_test_data.py
sqlshell/db/__init__.py
sqlshell/db/database_manager.py
sqlshell/db/export_manager.py
sqlshell/resources/__init__.py
sqlshell/resources/icon.png
sqlshell/resources/logo_large.png
sqlshell/resources/logo_medium.png
sqlshell/resources/logo_original.png
sqlshell/resources/logo_small.png
sqlshell/resources/splash_screen.gif
sqlshell/sqlshell/__init__.py
sqlshell/sqlshell/create_test_data.py
sqlshell/sqlshell/create_test_databases.py
sqlshell/ui/__init__.py
sqlshell/ui/bar_chart_delegate.py
sqlshell/ui/filter_header.py
sqlshell/utils/__init__.py
sqlshell/utils/clipboard_data_parser.py
sqlshell/utils/profile_categorize.py
sqlshell/utils/profile_cn2.py
sqlshell/utils/profile_column.py
sqlshell/utils/profile_compare.py
sqlshell/utils/profile_distributions.py
sqlshell/utils/profile_entropy.py
sqlshell/utils/profile_foreign_keys.py
sqlshell/utils/profile_keys.py
sqlshell/utils/profile_ohe.py
sqlshell/utils/profile_ohe_advanced.py
sqlshell/utils/profile_ohe_comparison.py
sqlshell/utils/profile_similarity.py
sqlshell/utils/search_in_df.py
sqlshell/utils/table_join_operations.py
sqlshell/utils/table_set_operations.py
sqlshell-5.0.5.dist-info/licenses/LICENSE
sqlshell-5.0.5.dist-info/METADATA
sqlshell-5.0.5.dist-info/WHEEL
sqlshell-5.0.5.dist-info/entry_points.txt
sqlshell-5.0.5.dist-info/top_level.txt
sqlshell-5.0.5.dist-info/RECORD
