Metadata-Version: 2.4
Name: sqlshell
Version: 5.0.5
Summary: A powerful SQL shell with GUI interface for data analysis
Author: SQLShell Team
License-Expression: MIT
Project-URL: Homepage, https://github.com/oyvinrog/SQLShell
Keywords: sql,data analysis,gui,duckdb
Classifier: Development Status :: 3 - Alpha
Classifier: Intended Audience :: Developers
Classifier: Programming Language :: Python :: 3
Classifier: Programming Language :: Python :: 3.8
Classifier: Programming Language :: Python :: 3.9
Classifier: Programming Language :: Python :: 3.10
Classifier: Programming Language :: Python :: 3.11
Requires-Python: >=3.8
License-File: LICENSE
Requires-Dist: pandas>=2.0.0
Requires-Dist: numpy>=1.24.0
Requires-Dist: PyQt6>=6.4.0
Requires-Dist: duckdb>=0.9.0
Requires-Dist: openpyxl>=3.1.0
Requires-Dist: fastparquet>=2023.10.1
Requires-Dist: pyarrow>=10.0.0
Requires-Dist: xlrd>=2.0.1
Requires-Dist: deltalake
Requires-Dist: scikit-learn
Requires-Dist: matplotlib>=3.10.0
Requires-Dist: scipy>=1.15.0
Requires-Dist: seaborn>=0.13.0
Requires-Dist: nltk>=3.8.1
Requires-Dist: psutil>=5.9.0
Dynamic: license-file
